{
  "headers": {
    "server-timing": "fetchSource;dur=2",
    "cross-origin-resource-policy": "same-origin",
    "cache-control": "public, max-age=31536000, immutable",
    "date": "Fri, 24 Nov 2023 05:21:18 GMT",
    "x-frame-options": "DENY",
    "server": "deno/gcp-asia-southeast1",
    "x-content-type-options": "nosniff",
    "age": "20524685",
    "x-amz-cf-id": "d8JfoWysFy-wD_r8YUZaDxWYQ373lMT6rZZ-P0fUv3NrK6BLj-Z2_A==",
    "cross-origin-embedder-policy": "same-origin",
    "via": "http/2 edgeproxy-h",
    "accept-ranges": "bytes",
    "vary": "Accept-Encoding, Origin",
    "x-amz-version-id": "FLISe3tECyy0E5KhaHGtGg1_AcxN2.18",
    "x-cache": "Hit from cloudfront",
    "x-amz-replication-status": "COMPLETED",
    "cross-origin-opener-policy": "same-origin",
    "x-amz-cf-pop": "SIN52-P1",
    "last-modified": "Fri, 25 Mar 2022 13:32:48 GMT",
    "content-security-policy": "default-src 'none'; style-src 'unsafe-inline'; sandbox",
    "access-control-allow-origin": "*",
    "content-type": "application/javascript",
    "referrer-policy": "strict-origin-when-cross-origin",
    "strict-transport-security": "max-age=63072000; includeSubDomains; preload",
    "etag": "W/\"c0637f77531a33e6c764e57ff4b9bb39\""
  },
  "url": "https://deno.land/std@0.132.0/node/_crypto/crypto_browserify/browserify_aes/incr32.js",
  "now": {
    "secs_since_epoch": 1721327963,
    "nanos_since_epoch": 579051716
  }
}